Metadata-Version: 1.0
Name: django-memcached2
Version: 0.1
Summary: django-memcached2 displays statistics about your currently running memcached instances
Home-page: http://github.com/edavis/django-memcached
Author: Eric Davis
Author-email: ed@npri.org
License: BSD
Keywords: memcached,django,caching,caches
Platform: UNKNOWN
Classifier: Development Status :: 4 - Beta
Classifier: Environment :: Web Environment
Classifier: Framework :: Django
Classifier: Intended Audience :: Developers
Classifier: Intended Audience :: System Administrators
Classifier: License :: OSI Approved :: BSD License
Classifier: Programming Language :: Python
Classifier: Topic :: Software Development :: Libraries :: Python Modules
Classifier: Topic :: System :: Monitoring
